review.py
reviewer-0.0.2.dist-info/DESCRIPTION.rst
reviewer-0.0.2.dist-info/METADATA
reviewer-0.0.2.dist-info/RECORD
reviewer-0.0.2.dist-info/WHEEL
reviewer-0.0.2.dist-info/entry_points.txt
reviewer-0.0.2.dist-info/metadata.json
reviewer-0.0.2.dist-info/top_level.txt
