Metadata-Version: 2.0
Name: reviewer
Version: 0.0.2
Summary: Easily create and manage gitlab merge requests from the commandline
Home-page: https://github.com/sdiepend/review
Author: Stijn Diependaele
Author-email: sdiepend@gmail.com
License: MIT
Keywords: gitlab cli tool merge request
Platform: UNKNOWN
Classifier: Development Status :: 3 - Alpha
Classifier: Intended Audience :: Developers
Classifier: Topic :: Software Development :: Build Tools
Classifier: License :: OSI Approved :: MIT License
Classifier: Programming Language :: Python :: 3.5
Classifier: Programming Language :: Python :: 3.6
Requires-Dist: fire
Requires-Dist: requests
